panphon2-0.3.3.dist-info/METADATA
panphon2-0.3.3.dist-info/WHEEL
panphon2/__init__.py
panphon2/panphon2.cpython-311-darwin.so
panphon2-0.3.3.dist-info/RECORD
