Metadata-Version: 2.1
Name: panphon2
Version: 0.3.3
